{"images":["tex/largeBuildingsSurface_Color.tex","tex/columnSurface_Color.tex","tex/metroSurface_Color.tex","tex/clubSurface_Color.tex","tex/clubFenceSurface_Color.tex","tex/buildingSetSurface_Color.tex","tex/stopLightSurface_Color.tex","tex/carsSurface_Color.tex","tex/buildingSurface_Color.tex","tex/groundSurface_Color.tex","tex/backLightSurface_ColorAlpha.png","tex/frontLightSurface_ColorAlpha.png"],"materials":[{"type":"blinn","diffuse":[0.8,0.8,0.8,1],"specular":[0.2,0.2,0.2,1],"shininess":0.5,"name":"Mat"},{"type":"blinn","diffuseMapId":0,"emissiveMapId":0,"name":"largeBuildings"},{"type":"blinn","diffuseMapId":1,"emissiveMapId":1,"name":"column"},{"type":"blinn","diffuseMapId":2,"emissiveMapId":2,"name":"metro"},{"type":"blinn","diffuseMapId":3,"emissiveMapId":3,"name":"club"},{"type":"blinn","diffuseMapId":4,"emissiveMapId":4,"name":"clubFence"},{"type":"blinn","diffuseMapId":5,"emissiveMapId":5,"name":"buildingSet"},{"type":"blinn","diffuseMapId":6,"emissiveMapId":6,"name":"stopLight"},{"type":"blinn","diffuseMapId":7,"emissiveMapId":7,"name":"cars"},{"type":"blinn","diffuseMapId":8,"emissiveMapId":8,"name":"building"},{"type":"blinn","diffuseMapId":9,"emissiveMapId":9,"name":"ground"},{"type":"blinn","diffuseMapId":10,"emissiveMapId":10,"name":"backLight"},{"type":"blinn","diffuseMapId":11,"emissiveMapId":11,"name":"frontLight"}],"geometries":[{"type":"triangles","buffers":{"ids":{"constructorName":"Uint16Array","name":"ids","length":4818,"offset":0,"itemSize":1},"VERTEX":{"constructorName":"Float32Array","name":"VERTEX","length":12948,"offset":4818,"itemSize":3},"TEXCOORD":{"constructorName":"Float32Array","name":"TEXCOORD","length":8632,"offset":17766,"itemSize":2}}},{"type":"triangles","buffers":{"ids":{"constructorName":"Uint16Array","name":"ids","length":4896,"offset":26398,"itemSize":1},"VERTEX":{"constructorName":"Float32Array","name":"VERTEX","length":8880,"offset":31294,"itemSize":3},"TEXCOORD":{"constructorName":"Float32Array","name":"TEXCOORD","length":5920,"offset":40174,"itemSize":2}}},{"type":"triangles","buffers":{"ids":{"constructorName":"Uint16Array","name":"ids","length":3468,"offset":46094,"itemSize":1},"VERTEX":{"constructorName":"Float32Array","name":"VERTEX","length":8640,"offset":49562,"itemSize":3},"TEXCOORD":{"constructorName":"Float32Array","name":"TEXCOORD","length":5760,"offset":58202,"itemSize":2}}},{"type":"triangles","buffers":{"ids":{"constructorName":"Uint16Array","name":"ids","length":85536,"offset":63962,"itemSize":1},"VERTEX":{"constructorName":"Float32Array","name":"VERTEX","length":145728,"offset":149498,"itemSize":3},"TEXCOORD":{"constructorName":"Float32Array","name":"TEXCOORD","length":97152,"offset":295226,"itemSize":2}}},{"type":"triangles","buffers":{"ids":{"constructorName":"Uint16Array","name":"ids","length":7656,"offset":392378,"itemSize":1},"VERTEX":{"constructorName":"Float32Array","name":"VERTEX","length":17880,"offset":400034,"itemSize":3},"TEXCOORD":{"constructorName":"Float32Array","name":"TEXCOORD","length":11920,"offset":417914,"itemSize":2}}},{"type":"triangles","buffers":{"ids":{"constructorName":"Uint16Array","name":"ids","length":11808,"offset":429834,"itemSize":1},"VERTEX":{"constructorName":"Float32Array","name":"VERTEX","length":27648,"offset":441642,"itemSize":3},"TEXCOORD":{"constructorName":"Float32Array","name":"TEXCOORD","length":18432,"offset":469290,"itemSize":2}}},{"type":"triangles","buffers":{"ids":{"constructorName":"Uint16Array","name":"ids","length":30924,"offset":487722,"itemSize":1},"VERTEX":{"constructorName":"Float32Array","name":"VERTEX","length":75684,"offset":518646,"itemSize":3},"TEXCOORD":{"constructorName":"Float32Array","name":"TEXCOORD","length":50456,"offset":594330,"itemSize":2}}},{"type":"triangles","buffers":{"ids":{"constructorName":"Uint16Array","name":"ids","length":44928,"offset":644786,"itemSize":1},"VERTEX":{"constructorName":"Float32Array","name":"VERTEX","length":116736,"offset":689714,"itemSize":3},"TEXCOORD":{"constructorName":"Float32Array","name":"TEXCOORD","length":77824,"offset":806450,"itemSize":2}}},{"type":"triangles","buffers":{"ids":{"constructorName":"Uint16Array","name":"ids","length":1056,"offset":884274,"itemSize":1},"VERTEX":{"constructorName":"Float32Array","name":"VERTEX","length":4752,"offset":885330,"itemSize":3},"TEXCOORD":{"constructorName":"Float32Array","name":"TEXCOORD","length":3168,"offset":890082,"itemSize":2}}},{"type":"triangles","buffers":{"ids":{"constructorName":"Uint16Array","name":"ids","length":1056,"offset":893250,"itemSize":1},"VERTEX":{"constructorName":"Float32Array","name":"VERTEX","length":4752,"offset":894306,"itemSize":3},"TEXCOORD":{"constructorName":"Float32Array","name":"TEXCOORD","length":3168,"offset":899058,"itemSize":2}}},{"type":"triangles","buffers":{"ids":{"constructorName":"Uint16Array","name":"ids","length":138,"offset":902226,"itemSize":1},"VERTEX":{"constructorName":"Float32Array","name":"VERTEX","length":240,"offset":902364,"itemSize":3},"TEXCOORD":{"constructorName":"Float32Array","name":"TEXCOORD","length":160,"offset":902604,"itemSize":2}}},{"type":"triangles","buffers":{"ids":{"constructorName":"Uint16Array","name":"ids","length":209664,"offset":902764,"itemSize":1},"VERTEX":{"constructorName":"Float32Array","name":"VERTEX","length":455040,"offset":1112428,"itemSize":3},"TEXCOORD":{"constructorName":"Float32Array","name":"TEXCOORD","length":303360,"offset":1567468,"itemSize":2}}},{"type":"triangles","buffers":{"ids":{"constructorName":"Uint16Array","name":"ids","length":209664,"offset":1870828,"itemSize":1},"VERTEX":{"constructorName":"Float32Array","name":"VERTEX","length":455040,"offset":2080492,"itemSize":3},"TEXCOORD":{"constructorName":"Float32Array","name":"TEXCOORD","length":303360,"offset":2535532,"itemSize":2}}}],"scenes":[{"name":"building02","scale":{"x":1,"y":1,"z":1},"rotation":{"x":0,"y":4.1887902047863905,"z":0},"position":{"x":-27269.8,"y":65.544,"z":-34531},"type":"mesh","geometryId":12,"materialId":9},{"name":"building01","scale":{"x":1,"y":1,"z":1},"rotation":{"x":0,"y":4.1887902047863905,"z":0},"position":{"x":-27269.8,"y":65.544,"z":-34531},"type":"mesh","geometryId":11,"materialId":9},{"name":"ground","scale":{"x":1,"y":1,"z":1},"rotation":{"x":-1.5707963267948966,"y":0,"z":0},"position":{"x":-24316.3,"y":-1,"z":-36997},"type":"mesh","geometryId":10,"materialId":10},{"name":"frontLight","scale":{"x":1,"y":1,"z":1},"rotation":{"x":1.4901167367922068e-8,"y":4.209507263007564,"z":0},"position":{"x":-27666,"y":73.0451,"z":-34416},"type":"mesh","geometryId":9,"materialId":12},{"name":"backLight","scale":{"x":1,"y":1,"z":1},"rotation":{"x":1.4901167367922068e-8,"y":1.0679146094177705,"z":0},"position":{"x":-27600,"y":73.0451,"z":-34472.3},"type":"mesh","geometryId":8,"materialId":11},{"name":"stopLight","scale":{"x":1,"y":1,"z":1},"rotation":{"x":0,"y":2.6179938779914944,"z":0},"position":{"x":-27215,"y":65.544,"z":-34714.2},"type":"mesh","geometryId":7,"materialId":7},{"name":"buildingSet","scale":{"x":1,"y":1,"z":1},"rotation":{"x":-1.401349291035775e-9,"y":1.2706590366464396,"z":0},"position":{"x":-35461.5,"y":58.5227,"z":-19688.8},"type":"mesh","geometryId":6,"materialId":6},{"name":"clubFence","scale":{"x":1,"y":1,"z":1},"rotation":{"x":5.9124424674709505e-25,"y":4.196155494229807,"z":0},"position":{"x":-35528.6,"y":60.7983,"z":-20736.4},"type":"mesh","geometryId":5,"materialId":5},{"name":"club","scale":{"x":1,"y":1,"z":1},"rotation":{"x":0,"y":5.766951821024705,"z":-2.1073454454429932e-8},"position":{"x":-35665,"y":154.989,"z":-20447.7},"type":"mesh","geometryId":4,"materialId":4},{"name":"cars","scale":{"x":1,"y":1,"z":1},"rotation":{"x":0,"y":2.6439469239686497,"z":0},"position":{"x":-27643.9,"y":92.0998,"z":-34435.5},"type":"mesh","geometryId":3,"materialId":8},{"name":"metro","scale":{"x":1,"y":1,"z":1},"rotation":{"x":0,"y":1.0418760423072668,"z":0},"position":{"x":-27326,"y":60.8824,"z":-35145.5},"type":"mesh","geometryId":2,"materialId":3},{"name":"column","scale":{"x":1,"y":1,"z":1},"rotation":{"x":0,"y":4.208529878626447,"z":0},"position":{"x":-32247.3,"y":65.544,"z":-26698.5},"type":"mesh","geometryId":1,"materialId":2},{"name":"largeBuildings","scale":{"x":1,"y":1,"z":1},"rotation":{"x":-1.5707963267948966,"y":0,"z":0},"position":{"x":-34379.8,"y":60.544,"z":-21060.2},"type":"mesh","geometryId":0,"materialId":1},{"type":"group","children":[12,11,10,9,8,7,6,5,4,3,2,1,0]}]}
